simpleinflux/__init__.py
simpleinflux/simpleinflux.py
simpleinflux-0.1.0.dist-info/LICENSE
simpleinflux-0.1.0.dist-info/WHEEL
simpleinflux-0.1.0.dist-info/METADATA
simpleinflux-0.1.0.dist-info/RECORD
