Metadata-Version: 2.1
Name: simpleinflux
Version: 0.1.0
Summary: simpleinflux - A simple frontend for InfluxDB 
Author-email: Christoph Kattmann <christoph.kattmann@gmail.com>
Classifier: License :: OSI Approved :: MIT License
Project-URL: Home, https://github.com/ckattmann/simpleinflux
